galibrate/__init__.py
galibrate/gao.py
galibrate/run_gao_numba.py
galibrate/run_gao_py.py
galibrate/sampled_parameter.py
galibrate/pysb_utils/__init__.py
galibrate/pysb_utils/fitness.py
galibrate/pysb_utils/galibrate_it.py
galibrate-0.4.2.dist-info/LICENSE
galibrate-0.4.2.dist-info/METADATA
galibrate-0.4.2.dist-info/WHEEL
galibrate-0.4.2.dist-info/top_level.txt
galibrate-0.4.2.dist-info/RECORD
