Metadata-Version: 2.1
Name: galibrate
Version: 0.4.2
Summary: Python toolkit for continuous Genetic Algorithm optimization.
Home-page: https://github.com/blakeaw/GAlibrate
Author: Blake A. Wilson
Author-email: blakeaw1102@gmail.com
License: UNKNOWN
Platform: UNKNOWN
Classifier: Programming Language :: Python :: 3
Classifier: License :: OSI Approved :: MIT License
Classifier: Operating System :: OS Independent
Requires-Python: >=3.6
Requires-Dist: numpy
Requires-Dist: scipy
